pysigrok_vcd.py
pysigrok_vcd-0.1.1.dist-info/entry_points.txt
pysigrok_vcd-0.1.1.dist-info/LICENSE
pysigrok_vcd-0.1.1.dist-info/WHEEL
pysigrok_vcd-0.1.1.dist-info/METADATA
pysigrok_vcd-0.1.1.dist-info/RECORD
