Metadata-Version: 2.1
Name: pysigrok_vcd
Version: 0.1.1
Summary: PySigrok driver for value change dump (VCD)
Author-email: Scott Shawcroft <scott@tannewt.org>
Requires-Python: >=3.7
Classifier: License :: OSI Approved :: MIT License
Requires-Dist: pysigrok >= 0.4.0
Requires-Dist: pyvcd < 0.4.0
Project-URL: Home, https://github.com/pysigrok/format-vcd
